<?xml version="1.0" encoding="UTF-8"?>
<node nodeName="MonternetSp" nodeType="Object" classType="test.xml.read.Smsp">
	<node nodeName="SpName" fieldName="spName" nodeType="String" />
	<node nodeName="GWCode" fieldName="gwCode" nodeType="String" />
	<node nodeName="PlateformIP" fieldName="ip" nodeType="String" />
	<node nodeName="ProcId" fieldName="id" nodeType="String" />
	<node nodeName="ProvinceList" fieldName="provinceList" nodeType="Object" classType="java.util.ArrayList">
		<node nodeName="Province" fieldName="i" nodeType="Object" classType="test.xml.read.Province">
			<node nodeName="Status" fieldName="status" nodeType="String" />
			<node nodeName="ProvinceCode" fieldName="provinceCode" nodeType="String" />
			<node nodeName="GWCode" fieldName="gwCode" nodeType="String" />
			<node nodeName="SpId" fieldName="spId" nodeType="String" />
		</node>
	</node>
</node>